LICENSE
README.md
setup.py
Amino.ed.egg-info/PKG-INFO
Amino.ed.egg-info/SOURCES.txt
Amino.ed.egg-info/dependency_links.txt
Amino.ed.egg-info/requires.txt
Amino.ed.egg-info/top_level.txt
aminoed/__init__.py
aminoed/client.py
aminoed/http.py
aminoed/websocket.py
aminoed/helpers/__init__.py
aminoed/helpers/event.py
aminoed/helpers/exceptions.py
aminoed/helpers/models.py
aminoed/helpers/types.py
aminoed/helpers/utils.py